Metadata-Version: 2.1
Name: minnow
Version: 2020.274.0
Summary: Utilities for the Minnow file processing framework.
Home-page: https://github.com/gershwinlabs/minnow-python
Author: Bill Allen
Author-email: photo.allen@gmail.com
License: MIT
Keywords: minnow,file,processing,properties
Platform: UNKNOWN
Classifier: Development Status :: 4 - Beta
Classifier: Topic :: Utilities
Classifier: License :: OSI Approved :: MIT License
Requires-Python: >=3.5, <4
